getlatesttinderbox
