Metadata-Version: 1.0
Name: GetLatestTinderbox
Version: 0.2.10
Summary: get latest mozilla firefox tinderbox build
Home-page: http://hg.mozilla.org/automation/getlatest-tinderbox/
Author: Jeff Hammel
Author-email: jhammel@mozilla.com
License: MPL
Platform: UNKNOWN
